CHANGELOG.md
LICENSE
README.md
hdem.py
hetzner_dns_manager-0.2.1.dist-info/METADATA
hetzner_dns_manager-0.2.1.dist-info/WHEEL
hetzner_dns_manager-0.2.1.dist-info/entry_points.txt
hetzner_dns_manager-0.2.1.dist-info/licenses/LICENSE
hetzner_dns_manager-0.2.1.dist-info/RECORD
