Metadata-Version: 2.4
Name: hetzner-dns-manager
Version: 0.2.1
Summary: Hetzner DNS Zone Manager
Project-URL: Homepage, https://github.com/serpent213/hetzner-dns-manager
Project-URL: Bug Tracker, https://github.com/serpent213/hetzner-dns-manager/issues
Project-URL: Changelog, https://github.com/serpent213/hetzner-dns-manager/blob/master/CHANGELOG.md
Author-email: Steffen Beyer <steffen@beyer.io>
License-Expression: BSD-2-Clause
License-File: LICENSE
Classifier: Development Status :: 4 - Beta
Classifier: Environment :: Console
Classifier: Intended Audience :: System Administrators
Classifier: Operating System :: OS Independent
Classifier: Programming Language :: Python :: 3
Classifier: Programming Language :: Python :: 3.10
Classifier: Programming Language :: Python :: 3.11
Classifier: Programming Language :: Python :: 3.12
Classifier: Programming Language :: Python :: 3.13
Classifier: Topic :: Internet :: Name Service (DNS)
Classifier: Topic :: System :: Systems Administration
Requires-Python: >=3.10
Requires-Dist: click
Requires-Dist: dnspython
Requires-Dist: requests
Requires-Dist: rich
Requires-Dist: ruamel-yaml
